huaban_exporter.py
huaban_exporter-0.0.3.dist-info/RECORD
huaban_exporter-0.0.3.dist-info/WHEEL
huaban_exporter-0.0.3.dist-info/top_level.txt
huaban_exporter-0.0.3.dist-info/DESCRIPTION.rst
huaban_exporter-0.0.3.dist-info/METADATA
huaban_exporter-0.0.3.dist-info/metadata.json
huaban_exporter-0.0.3.dist-info/entry_points.txt
