Metadata-Version: 2.0
Name: huaban-exporter
Version: 0.0.3
Summary: Backup tool for huaban user.Save pictures from huaban.
Home-page: https://github.com/winkidney/huaban-exporter
Author: winkidney
Author-email: winkidney@gmail.com
License: MIT
Platform: UNKNOWN
Requires-Dist: cmdtree
Requires-Dist: requests
Requires-Dist: tqdm
